calculemus/__init__.py
calculemus/version.py
calculemus/core/__init__.py
calculemus-0.0.2.dist-info/LICENSE
calculemus-0.0.2.dist-info/METADATA
calculemus-0.0.2.dist-info/WHEEL
calculemus-0.0.2.dist-info/top_level.txt
calculemus-0.0.2.dist-info/RECORD
