Metadata-Version: 2.1
Name: calculemus
Version: 0.0.2
Summary: Logical verification of probabilistic/language model 'intuitions'.
Author-email: Alexander Fedotov <alex.fedotov@aol.com>
Project-URL: Homepage, https://github.com/machina-ratiocinatrix/calculemus
Project-URL: Bug Tracker, https://github.com/machina-ratiocinatrix/calculemus/issues
Classifier: Programming Language :: Python :: 3
Classifier: License :: OSI Approved :: MIT License
Classifier: Operating System :: OS Independent
Requires-Python: >=3.10
License-File: LICENSE
